minrpc/__init__.py
minrpc/client.py
minrpc/connection.py
minrpc/ipc.py
minrpc/posix.py
minrpc/service.py
minrpc/windows.py
minrpc-0.2.0.dist-info/licenses/COPYING.rst
minrpc-0.2.0.dist-info/METADATA
minrpc-0.2.0.dist-info/WHEEL
minrpc-0.2.0.dist-info/top_level.txt
minrpc-0.2.0.dist-info/zip-safe
minrpc-0.2.0.dist-info/RECORD
