Metadata-Version: 2.4
Name: minrpc
Version: 0.2.0
Summary: Minimalistic RPC utility (DO NOT USE!)
Home-page: https://github.com/hibtc/minrpc
Author: Thomas Gläßle
Author-email: t_glaessle@gmx.de
License: GPLv3+
Classifier: Development Status :: 4 - Beta
Classifier: Intended Audience :: Science/Research
Classifier: License :: OSI Approved :: GNU General Public License v3 or later (GPLv3+)
Classifier: Operating System :: Microsoft :: Windows
Classifier: Operating System :: POSIX :: Linux
Classifier: Programming Language :: Python :: 3
Classifier: Topic :: Software Development :: Libraries
Requires-Python: >=3.4
License-File: COPYING.rst
Dynamic: license-file
